<text text-cts="urn:cts:greekLit:tlg0057.tlg035.1st1K-grc2" author="Galen" title="De venereis" file-name="tlg0057.tlg035.1st1K-grc2.xml" date-of-conversion="2017-03-29">
  <sentence n="position in the document">
    <token p="passage-level cts urn" n="position in @p" a="nth occurrence in @p" o="Mate tagger POS tag" u="position in s element" join="optional: join b(ack) or a(fter) for punctuation marks" tag="optional: selection of editorial tags containing the token in the original document, such as del or add">
      <wordForm>word form of the token</wordForm>
      <lemma id="contains the id number of the entry in the database consisting of the set of all word forms + morphological analyses of all Greek texts">
        <l1>as many l1 elements as the lemmas found in PerseusUnderPhilologic for 
              the relevant word form AND morphological analysis</l1>
        <l2>as many l2 elements as the lemmas found in Morpheus for 
              the relevant word form AND morphological analysis</l2>
      </lemma>
    </token>
  </sentence>
  <s n="1">
    <t p="1" n="1" a="[1]" o="n-s---mv-" u="1">
      <f>ΓΑΛΗΝΟΥ</f>
      <l i="393864"/>
    </t>
    <t p="1" n="2" a="[1]" o="n-s---mv-" u="2">
      <f>ΠΕΡΙ</f>
      <l i="259846"/>
    </t>
    <t p="1" n="3" a="[1]" o="a-s---mv-" u="3">
      <f>ΑΦΡΟΔΙΣΙΩΝ</f>
      <l i="425198"/>
    </t>
    <t p="1" n="4" a="[1]" o="u--------" u="4" join="b">
      <f>.</f>
      <l>
        <l2>.</l2>
      </l>
    </t>
  </s>
  <s n="2">
    <t p="1" n="5" a="[1]" o="n-p---mg-" u="1">
      <f>Ἀφροδισίων</f>
      <l i="104137"/>
    </t>
    <t p="1" n="6" a="[1]" o="g--------" u="2">
      <f>μὲν</f>
      <l>
        <l1 o="g---------">μέν</l1>
      </l>
    </t>
    <t p="1" n="7" a="[1]" o="r--------" u="3">
      <f>κατὰ</f>
      <l>
        <l2>κατά</l2>
      </l>
    </t>
    <t p="1" n="8" a="[2]" o="g--------" u="4">
      <f>μὲν</f>
      <l>
        <l1 o="g---------">μέν</l1>
      </l>
    </t>
    <t p="1" n="9" a="[1]" o="n-s---ma-" u="5">
      <f>Ἐπίκουρον</f>
      <l i="94059">
        <l1 o="ne-s---ma-">Ἐπίκουρος</l1>
      </l>
    </t>
    <t p="1" n="10" a="[1]" o="a-s---fn-" u="6">
      <f>οὐδεμία</f>
      <l i="22808">
        <l1 o="a--s---fn-">οὐδείς</l1>
      </l>
    </t>
    <t p="1" n="11" a="[1]" o="n-s---fn-" u="7">
      <f>χρῆσις</f>
      <l i="35976">
        <l1 o="n--s---fn-">χρῆσις</l1>
      </l>
    </t>
    <t p="1" n="12" a="[1]" o="a-s---fn-" u="8">
      <f>ὑγιεινή</f>
      <l i="399714">
        <l2>ὑγιεινός</l2>
      </l>
    </t>
    <t p="1" n="13" a="[1]" o="u--------" u="9" join="b">
      <f>·</f>
      <l>
        <l2>·</l2>
      </l>
    </t>
  </s>
  <s n="3">
    <t p="1" n="14" a="[2]" o="r--------" u="1">
      <f>κατὰ</f>
      <l>
        <l2>κατά</l2>
      </l>
    </t>
    <t p="1" n="15" a="[1]" o="g--------" u="2">
      <f>δὲ</f>
      <l>
        <l1 o="g---------">δέ</l1>
      </l>
    </t>
    <t p="1" n="16" a="[1]" o="a-s---na-" u="3">
      <f>τἀληθὲς</f>
      <l i="89641">
        <l1 o="a--s---na-">ἀληθής</l1>
      </l>
    </t>
    <t p="1" n="17" a="[1]" o="r--------" u="4">
      <f>ἐκ</f>
      <l>
        <l2>ἐκ</l2>
      </l>
    </t>
    <t p="1" n="18" a="[1]" o="n-p---ng-" u="5">
      <f>διαλειμμάτων</f>
      <l i="59176">
        <l1 o="n--p---ng-">διάλειμμα</l1>
      </l>
    </t>
    <t p="1" n="19" a="[1]" o="a-p---ng-" u="6">
      <f>τηλικούτων</f>
      <l i="130245">
        <l2>τηλικοῦτος</l2>
      </l>
    </t>
    <t p="1" n="20" a="[1]" o="u--------" u="7" join="b">
      <f>,</f>
      <l>
        <l2>,</l2>
      </l>
    </t>
    <t p="1" n="21" a="[1]" o="c--------" u="8">
      <f>ὡς</f>
      <l i="436">
        <l1 o="c---------">ὡς</l1>
      </l>
    </t>
    <t p="1" n="22" a="[1]" o="r--------" u="9">
      <f>ἐπὶ</f>
      <l>
        <l2>ἐπί</l2>
      </l>
    </t>
    <t p="1" n="23" a="[1]" o="l-p---fd-" u="10">
      <f>ταῖς</f>
      <l i="12710">
        <l2>ὁ</l2>
      </l>
    </t>
    <t p="1" n="24" a="[1]" o="n-p---fd-" u="11">
      <f>χρήσεσιν</f>
      <l i="425199"/>
    </t>
    <t p="1" n="25" a="[1]" o="n-s---ma-" u="12">
      <f>ἄνθρωπον</f>
      <l i="18955">
        <l1 o="n--s---ma-">ἄνθρωπος</l1>
      </l>
    </t>
    <t p="1" n="26" a="[1]" o="a-s---ma-" u="13">
      <f>αὐτὸν</f>
      <l i="427">
        <l1 o="a--s---ma-">αὐτός</l1>
      </l>
    </t>
    <t p="1" n="27" a="[1]" o="p-s---mg-" u="14">
      <f>αὑτοῦ</f>
      <l i="17978">
        <l1 o="pk-s---mg-">ἑαυτοῦ</l1>
      </l>
    </t>
    <t p="1" n="28" a="[1]" o="a-s---nac" u="15">
      <f>κουφότερον</f>
      <l i="75692">
        <l1 o="a--s---nac">κοῦφος</l1>
      </l>
    </t>
    <t p="1" n="29" a="[1]" o="d--------" u="16">
      <f>καὶ</f>
      <l i="13">
        <l1 o="d---------">καί</l1>
      </l>
    </t>
    <t p="1" n="30" a="[1]" o="a-s---nac" u="17">
      <f>εὐπνούστερον</f>
      <l i="396714"/>
    </t>
    <t p="1" n="31" a="[1]" o="v--pna---" u="18">
      <f>δοκεῖν</f>
      <l i="17224">
        <l1 o="v---pna---">δοκέω</l1>
      </l>
    </t>
    <t p="1" n="32" a="[1]" o="v--rna---" u="19">
      <f>γεγονέναι</f>
      <l i="45203">
        <l1 o="v---rna---">γίγνομαι</l1>
      </l>
    </t>
    <t p="1" n="33" a="[2]" o="u--------" u="20" join="b">
      <f>.</f>
      <l>
        <l2>.</l2>
      </l>
    </t>
  </s>
  <s n="4">
    <t p="1" n="34" a="[1]" o="l-s---mn-" u="1">
      <f>ὁ</f>
      <l i="394">
        <l2>ὁ</l2>
      </l>
    </t>
    <t p="1" n="35" a="[2]" o="g--------" u="2">
      <f>δὲ</f>
      <l>
        <l1 o="g---------">δέ</l1>
      </l>
    </t>
    <t p="1" n="36" a="[1]" o="n-s---mn-" u="3">
      <f>καιρὸς</f>
      <l i="22323">
        <l1 o="n--s---mn-">καιρός</l1>
      </l>
    </t>
    <t p="1" n="37" a="[1]" o="l-s---fg-" u="4">
      <f>τῆς</f>
      <l i="3017">
        <l2>ὁ</l2>
      </l>
    </t>
    <t p="1" n="38" a="[1]" o="n-s---fg-" u="5">
      <f>χρήσεως</f>
      <l i="82728">
        <l1 o="n--s---fg-">χρῆσις</l1>
      </l>
    </t>
    <t p="1" n="39" a="[2]" o="u--------" u="6" join="b">
      <f>,</f>
      <l>
        <l2>,</l2>
      </l>
    </t>
    <t p="1" n="40" a="[1]" o="c--------" u="7">
      <f>ὅταν</f>
      <l i="4528">
        <l1 o="c---------">ὅταν</l1>
      </l>
    </t>
    <t p="1" n="41" a="[1]" o="d--------" u="8">
      <f>ἀκριβῶς</f>
      <l i="19395">
        <l1 o="d---------">ἀκριβής</l1>
        <l2>ἀκριβῶς</l2>
      </l>
    </t>
    <t p="1" n="42" a="[1]" o="a-s---na-" u="9">
      <f>μέσον</f>
      <l i="4000">
        <l1 o="a--s---na-">μέσος</l1>
      </l>
    </t>
    <t p="1" n="43" a="[1]" o="v3spsa---" u="10">
      <f>ᾖ</f>
      <l i="16195">
        <l1 o="vc3spsa---">εἰμί</l1>
      </l>
    </t>
    <t p="1" n="44" a="[1]" o="l-p---fg-" u="11">
      <f>τῶν</f>
      <l i="15336">
        <l2>ὁ</l2>
      </l>
    </t>
    <t p="1" n="45" a="[1]" o="d--------" u="12">
      <f>ἔξωθεν</f>
      <l i="18100">
        <l1 o="d---------">ἔξωθεν</l1>
      </l>
    </t>
    <t p="1" n="46" a="[1]" o="n-p---fg-" u="13">
      <f>περιστάσεων</f>
      <l i="286374">
        <l1 o="n--p---fg-">περίστασις</l1>
      </l>
    </t>
    <t p="1" n="47" a="[1]" o="a-p---fg-" u="14">
      <f>ἁπασῶν</f>
      <l i="32379">
        <l1 o="a--p---fg-">ἅπας</l1>
      </l>
    </t>
    <t p="1" n="48" a="[1]" o="l-s---na-" u="15">
      <f>τὸ</f>
      <l i="254">
        <l2>ὁ</l2>
      </l>
    </t>
    <t p="1" n="49" a="[1]" o="n-s---na-" u="16">
      <f>σῶμα</f>
      <l i="16074">
        <l1 o="n--s---na-">σῶμα</l1>
      </l>
    </t>
    <t p="1" n="50" a="[3]" o="u--------" u="17" join="b">
      <f>,</f>
      <l>
        <l2>,</l2>
      </l>
    </t>
    <t p="1" n="51" a="[1]" o="c--------" u="18">
      <f>μήθ’</f>
      <l i="341889"/>
    </t>
    <t p="1" n="52" a="[1]" o="v-srpema-" u="19">
      <f>ὑπερπεπληρωμένον</f>
      <l i="396715"/>
    </t>
    <t p="1" n="53" a="[4]" o="u--------" u="20" join="b">
      <f>,</f>
      <l>
        <l2>,</l2>
      </l>
    </t>
    <t p="1" n="54" a="[1]" o="u--------" u="21">
      <f>μήτ’</f>
      <l>
        <l2>μήτ’</l2>
      </l>
    </t>
    <t p="1" n="55" a="[1]" o="a-s---mv-" u="22">
      <f>ἐνδεὲς</f>
      <l i="396716">
        <l1 o="a--s---mv-">ἐνδεής</l1>
      </l>
    </t>
    <t p="1" n="56" a="[5]" o="u--------" u="23" join="b">
      <f>,</f>
      <l>
        <l2>,</l2>
      </l>
    </t>
    <t p="1" n="57" a="[2]" o="n-s---mv-" u="24">
      <f>μήθ’</f>
      <l i="396717"/>
    </t>
    <t p="1" n="58" a="[1]" o="v-srpema-" u="25">
      <f>ὑπερεψυγμένον</f>
      <l i="396718"/>
    </t>
    <t p="1" n="59" a="[6]" o="u--------" u="26" join="b">
      <f>,</f>
      <l>
        <l2>,</l2>
      </l>
    </t>
    <t p="1" n="60" a="[3]" o="d--------" u="27">
      <f>μήθ’</f>
      <l i="341890"/>
    </t>
    <t p="1" n="61" a="[1]" o="v-srpenn-" u="28">
      <f>ὑπερτεθερμασμένον</f>
      <l i="396719"/>
    </t>
    <t p="1" n="62" a="[7]" o="u--------" u="29" join="b">
      <f>,</f>
      <l>
        <l2>,</l2>
      </l>
    </t>
    <t p="1" n="63" a="[2]" o="c--------" u="30">
      <f>μήτ’</f>
      <l i="346300"/>
    </t>
    <t p="1" n="64" a="[1]" o="v-srpema-" u="31">
      <f>ἐξηρασμένον</f>
      <l i="425200"/>
    </t>
    <t p="1" n="65" a="[8]" o="u--------" u="32" join="b">
      <f>,</f>
      <l>
        <l2>,</l2>
      </l>
    </t>
    <t p="1" n="66" a="[4]" o="d--------" u="33">
      <f>μήθ’</f>
      <l i="341890"/>
    </t>
    <t p="1" n="67" a="[1]" o="v-srpema-" u="34">
      <f>ὑγρασμένον</f>
      <l i="396721"/>
    </t>
    <t p="1" n="68" a="[1]" o="d--------" u="35">
      <f>ἀμέτρως</f>
      <l i="87342">
        <l1 o="d---------">ἄμετρος</l1>
      </l>
    </t>
    <t p="1" n="69" a="[3]" o="u--------" u="36" join="b">
      <f>.</f>
      <l>
        <l2>.</l2>
      </l>
    </t>
  </s>
  <s n="5">
    <t p="1" n="70" a="[1]" o="c--------" u="1">
      <f>εἰ</f>
      <l i="751">
        <l1 o="c---------">εἰ</l1>
      </l>
    </t>
    <t p="1" n="71" a="[3]" o="g--------" u="2">
      <f>δὲ</f>
      <l>
        <l1 o="g---------">δέ</l1>
      </l>
    </t>
    <t p="1" n="72" a="[2]" o="d--------" u="3">
      <f>καὶ</f>
      <l i="13">
        <l1 o="d---------">καί</l1>
      </l>
    </t>
    <t p="1" n="73" a="[1]" o="v3saia---" u="4">
      <f>διαμαρτάνοιέν</f>
      <l i="396722"/>
    </t>
    <t p="1" n="74" a="[1]" o="d--------" u="5">
      <f>ποτε</f>
      <l i="857">
        <l1 o="dx--------">ποτε</l1>
      </l>
    </t>
    <t p="1" n="75" a="[1]" o="r--------" u="6">
      <f>κατά</f>
      <l>
        <l2>κατά</l2>
      </l>
    </t>
    <t p="1" n="76" a="[1]" o="d--------" u="7">
      <f>τι</f>
      <l>
        <l2>τι</l2>
      </l>
    </t>
    <t p="1" n="77" a="[9]" o="u--------" u="8" join="b">
      <f>,</f>
      <l>
        <l2>,</l2>
      </l>
    </t>
    <t p="1" n="78" a="[1]" o="a-s---na-" u="9">
      <f>μικρὸν</f>
      <l i="20947">
        <l1 o="a--s---na-">μικρός</l1>
      </l>
    </t>
    <t p="1" n="79" a="[3]" o="g--------" u="10">
      <f>μὲν</f>
      <l>
        <l1 o="g---------">μέν</l1>
      </l>
    </t>
    <t p="1" n="80" a="[1]" o="v3spma---" u="11">
      <f>ἔστω</f>
      <l i="8604">
        <l1 o="vc3spma---">εἰμί</l1>
      </l>
    </t>
    <t p="1" n="81" a="[2]" o="l-s---na-" u="12">
      <f>τὸ</f>
      <l i="254">
        <l2>ὁ</l2>
      </l>
    </t>
    <t p="1" n="82" a="[1]" o="v-sppena-" u="13">
      <f>ἁμαρτανόμενον</f>
      <l i="425201">
        <l1 o="v--sppena-">ἁμαρτάνω</l1>
      </l>
    </t>
    <t p="1" n="83" a="[4]" o="u--------" u="14" join="b">
      <f>.</f>
      <l>
        <l2>.</l2>
      </l>
    </t>
  </s>
  <s n="6">
    <t p="1" n="84" a="[1]" o="a-s---nnc" u="1">
      <f>ἄμεινον</f>
      <l i="19977">
        <l1 o="a--s---nnc">ἀμείνων</l1>
      </l>
    </t>
    <t p="1" n="85" a="[4]" o="g--------" u="2">
      <f>δὲ</f>
      <l>
        <l1 o="g---------">δέ</l1>
      </l>
    </t>
    <t p="1" n="86" a="[1]" o="d--------" u="3">
      <f>τῷ</f>
      <l i="454">
        <l1 o="d---------">τῷ</l1>
      </l>
    </t>
    <t p="1" n="87" a="[1]" o="v-srpemd-" u="4">
      <f>τεθερμασμένῳ</f>
      <l i="396724"/>
    </t>
    <t p="1" n="88" a="[1]" o="d--------" u="5">
      <f>μᾶλλον</f>
      <l i="15214">
        <l2>μᾶλλον</l2>
      </l>
    </t>
    <t p="1" n="89" a="[1]" o="c--------" u="6">
      <f>ἢ</f>
      <l i="1427">
        <l1 o="c---------">ἤ</l1>
      </l>
    </t>
    <t p="1" n="90" a="[1]" o="v-sppemd-" u="7">
      <f>ἐψυγμένῳ</f>
      <l i="425202"/>
    </t>
    <t p="1" n="91" a="[10]" o="u--------" u="8" join="b">
      <f>,</f>
      <l>
        <l2>,</l2>
      </l>
    </t>
    <t p="1" n="92" a="[3]" o="d--------" u="9">
      <f>καὶ</f>
      <l i="13">
        <l1 o="d---------">καί</l1>
      </l>
    </t>
    <t p="1" n="93" a="[1]" o="v-sppemd-" u="10">
      <f>πεπληρωμένῳ</f>
      <l i="425203"/>
    </t>
    <t p="1" n="94" a="[2]" o="d--------" u="11">
      <f>μᾶλλον</f>
      <l i="15214">
        <l2>μᾶλλον</l2>
      </l>
    </t>
    <t p="1" n="95" a="[2]" o="c--------" u="12">
      <f>ἢ</f>
      <l i="1427">
        <l1 o="c---------">ἤ</l1>
      </l>
    </t>
    <t p="1" n="96" a="[1]" o="v-sppemd-" u="13">
      <f>κεκενωμένῳ</f>
      <l i="425204"/>
    </t>
    <t p="1" n="97" a="[11]" o="u--------" u="14" join="b">
      <f>,</f>
      <l>
        <l2>,</l2>
      </l>
    </t>
    <t p="1" n="98" a="[4]" o="d--------" u="15">
      <f>καὶ</f>
      <l i="13">
        <l1 o="d---------">καί</l1>
      </l>
    </t>
    <t p="1" n="99" a="[1]" o="v-srpemd-" u="16">
      <f>ὑγρασμένῳ</f>
      <l i="425205"/>
    </t>
    <t p="1" n="100" a="[3]" o="d--------" u="17">
      <f>μᾶλλον</f>
      <l i="15214">
        <l2>μᾶλλον</l2>
      </l>
    </t>
    <t p="1" n="101" a="[3]" o="c--------" u="18">
      <f>ἢ</f>
      <l i="1427">
        <l1 o="c---------">ἤ</l1>
      </l>
    </t>
    <t p="1" n="102" a="[1]" o="v-srpemd-" u="19">
      <f>ἐξηρασμένῳ</f>
      <l i="396728"/>
    </t>
    <t p="1" n="103" a="[2]" o="d--------" u="20">
      <f>τῷ</f>
      <l i="454">
        <l1 o="d---------">τῷ</l1>
      </l>
    </t>
    <t p="1" n="104" a="[1]" o="n-s---nd-" u="21">
      <f>σώματι</f>
      <l i="22633">
        <l1 o="n--s---nd-">σῶμα</l1>
      </l>
    </t>
    <t p="1" n="105" a="[1]" o="v--pne---" u="22">
      <f>χρῆσθαι</f>
      <l i="20882">
        <l1 o="v---pne---">χράω2</l1>
        <l2>χράομαι</l2>
        <l2>χραύω</l2>
        <l2>χράω</l2>
      </l>
    </t>
    <t p="1" n="106" a="[1]" o="l-p---md-" u="23">
      <f>τοῖς</f>
      <l i="1780">
        <l2>ὁ</l2>
      </l>
    </t>
    <t p="1" n="107" a="[1]" o="a-p---md-" u="24">
      <f>ἀφροδισίοις</f>
      <l i="99420">
        <l1 o="ae-p---md-">Ἀφροδίσιος</l1>
      </l>
    </t>
    <t p="1" n="108" a="[5]" o="u--------" u="25" join="b">
      <f>.</f>
      <l>
        <l2>.</l2>
      </l>
    </t>
  </s>
  <s n="7">
    <t p="1" n="109" a="[1]" o="l-p---mn-" u="1">
      <f>οἱ</f>
      <l i="109">
        <l2>ὁ</l2>
      </l>
    </t>
    <t p="1" n="110" a="[4]" o="g--------" u="2">
      <f>μὲν</f>
      <l>
        <l1 o="g---------">μέν</l1>
      </l>
    </t>
    <t p="1" n="111" a="[1]" o="g--------" u="3">
      <f>οὖν</f>
      <l>
        <l1 o="g---------">οὖν</l1>
      </l>
    </t>
    <t p="1" n="112" a="[1]" o="l-s---fa-" u="4">
      <f>τὴν</f>
      <l>
        <l2>ὁ</l2>
      </l>
    </t>
    <t p="1" n="113" a="[1]" o="a-s---fa-" u="5">
      <f>ἀσθενῆ</f>
      <l i="39173">
        <l1 o="a--s---fa-">ἀσθενής</l1>
      </l>
    </t>
    <t p="1" n="114" a="[1]" o="n-s---fa-" u="6">
      <f>δύναμιν</f>
      <l i="15592">
        <l1 o="n--s---fa-">δύναμις</l1>
      </l>
    </t>
    <t p="1" n="115" a="[1]" o="v-pppamn-" u="7">
      <f>ἔχοντες</f>
      <l i="3671">
        <l1 o="v--pppamn-">ἔχω</l1>
      </l>
    </t>
    <t p="1" n="116" a="[1]" o="r--------" u="8">
      <f>ἀπὸ</f>
      <l>
        <l2>ἀπό</l2>
      </l>
    </t>
    <t p="1" n="117" a="[2]" o="l-s---fg-" u="9">
      <f>τῆς</f>
      <l i="3017">
        <l2>ὁ</l2>
      </l>
    </t>
    <t p="1" n="118" a="[1]" o="n-s---fg-" u="10">
      <f>λαγνείας</f>
      <l i="101563">
        <l1 o="n--s---fg-">λαγνεία</l1>
      </l>
    </t>
    <t p="1" n="119" a="[1]" o="r--------" u="11">
      <f>εἰς</f>
      <l>
        <l2>εἰς</l2>
      </l>
    </t>
    <t p="1" n="120" a="[1]" o="a-s---fas" u="12">
      <f>ἐσχάτην</f>
      <l i="71083"/>
    </t>
    <t p="1" n="121" a="[1]" o="n-s---fa-" u="13">
      <f>ἀῤῥωστίαν</f>
      <l i="412870"/>
    </t>
    <t p="1" n="122" a="[1]" o="v3ppie---" u="14">
      <f>ἀφικνοῦνται</f>
      <l i="17465">
        <l2>ἀφικνέομαι</l2>
      </l>
    </t>
    <t p="1" n="123" a="[2]" o="u--------" u="15" join="b">
      <f>·</f>
      <l>
        <l2>·</l2>
      </l>
    </t>
  </s>
  <s n="8">
    <t p="1" n="124" a="[2]" o="l-p---mn-" u="1">
      <f>οἱ</f>
      <l i="109">
        <l2>ὁ</l2>
      </l>
    </t>
    <t p="1" n="125" a="[5]" o="g--------" u="2">
      <f>δὲ</f>
      <l>
        <l1 o="g---------">δέ</l1>
      </l>
    </t>
    <t p="1" n="126" a="[1]" o="a-s---fa-" u="3">
      <f>ἰσχυρὰν</f>
      <l i="17888">
        <l1 o="a--s---fa-">ἰσχυρός</l1>
      </l>
    </t>
    <t p="1" n="127" a="[5]" o="d--------" u="4">
      <f>καὶ</f>
      <l i="13">
        <l1 o="d---------">καί</l1>
      </l>
    </t>
    <t p="1" n="128" a="[1]" o="v-pppamn-" u="5">
      <f>νοσοῦντες</f>
      <l i="139646">
        <l1 o="v--pppamn-">νοσέω</l1>
      </l>
    </t>
    <t p="1" n="129" a="[2]" o="r--------" u="6">
      <f>ἀπὸ</f>
      <l>
        <l2>ἀπό</l2>
      </l>
    </t>
    <t p="1" n="130" a="[1]" o="n-s---ng-" u="7">
      <f>φλέγματος</f>
      <l i="76428">
        <l1 o="n--s---ng-">φλέγμα</l1>
      </l>
    </t>
    <t p="1" n="131" a="[1]" o="n-p---fa-" u="8">
      <f>περιουσίας</f>
      <l i="15502">
        <l1 o="n--p---fa-">περιουσία</l1>
      </l>
    </t>
    <t p="1" n="132" a="[3]" o="d--------" u="9">
      <f>τῷ</f>
      <l i="454">
        <l1 o="d---------">τῷ</l1>
      </l>
    </t>
    <t p="1" n="133" a="[1]" o="v--pna---" u="10">
      <f>διαφορεῖν</f>
      <l i="395754">
        <l2>διαφορέω</l2>
      </l>
    </t>
    <t p="1" n="134" a="[1]" o="v3piia---" u="11">
      <f>ἐπιπλέον</f>
      <l i="400239"/>
    </t>
    <t p="1" n="135" a="[1]" o="l-p---ma-" u="12">
      <f>τοὺς</f>
      <l>
        <l2>ὁ</l2>
      </l>
    </t>
    <t p="1" n="136" a="[1]" o="n-p---ma-" u="13">
      <f>χυμοὺς</f>
      <l i="79085">
        <l1 o="n--p---ma-">χυμός</l1>
      </l>
    </t>
    <t p="1" n="137" a="[1]" o="a-s---fa-" u="14">
      <f>ἀβλαβῆ</f>
      <l i="67149">
        <l1 o="a--s---fa-">ἀβλαβής</l1>
      </l>
    </t>
    <t p="1" n="138" a="[1]" o="v-pppamd-" u="15">
      <f>ἔχουσι</f>
      <l i="26665">
        <l1 o="v--pppamd-">ἔχω</l1>
      </l>
    </t>
    <t p="1" n="139" a="[2]" o="l-s---fa-" u="16">
      <f>τὴν</f>
      <l>
        <l2>ὁ</l2>
      </l>
    </t>
    <t p="1" n="140" a="[1]" o="n-s---fa-" u="17">
      <f>χρῆσιν</f>
      <l i="23347">
        <l1 o="n--s---fa-">χρῆσις</l1>
      </l>
    </t>
    <t p="1" n="141" a="[1]" o="p-p---mg-" u="18">
      <f>αὐτῶν</f>
      <l i="4117">
        <l1 o="pp-p---mg-">αὐτός</l1>
      </l>
    </t>
    <t p="1" n="142" a="[3]" o="u--------" u="19" join="b">
      <f>·</f>
      <l>
        <l2>·</l2>
      </l>
    </t>
  </s>
  <s n="9">
    <t p="1" n="143" a="[1]" o="d--------" u="1">
      <f>οὕτω</f>
      <l i="3584">
        <l1 o="dd--------">οὕτως</l1>
      </l>
    </t>
    <t p="1" n="144" a="[1]" o="g--------" u="2">
      <f>γὰρ</f>
      <l>
        <l1 o="g---------">γάρ</l1>
      </l>
    </t>
    <t p="1" n="145" a="[2]" o="l-p---md-" u="3">
      <f>τοῖς</f>
      <l i="1780">
        <l2>ὁ</l2>
      </l>
    </t>
    <t p="1" n="146" a="[1]" o="n-p---md-" u="4">
      <f>ὑγροῖς</f>
      <l i="53839"/>
    </t>
    <t p="1" n="147" a="[6]" o="d--------" u="5">
      <f>καὶ</f>
      <l i="13">
        <l1 o="d---------">καί</l1>
      </l>
    </t>
    <t p="1" n="148" a="[1]" o="a-p---md-" u="6">
      <f>θερμοῖς</f>
      <l i="71463">
        <l1 o="a--p---md-">θερμός</l1>
      </l>
    </t>
    <t p="1" n="149" a="[1]" o="v3spia---" u="7">
      <f>ἐστι</f>
      <l i="9261">
        <l1 o="vc3spia---">εἰμί</l1>
      </l>
    </t>
    <t p="1" n="150" a="[12]" o="u--------" u="8" join="b">
      <f>,</f>
      <l>
        <l2>,</l2>
      </l>
    </t>
    <t p="1" n="151" a="[7]" o="d--------" u="9">
      <f>καὶ</f>
      <l i="13">
        <l1 o="d---------">καί</l1>
      </l>
    </t>
    <t p="1" n="152" a="[1]" o="a-p---mn-" u="10">
      <f>ὅσοι</f>
      <l i="8537">
        <l2>ὅσος</l2>
      </l>
    </t>
    <t p="1" n="153" a="[1]" o="n-s---fd-" u="11">
      <f>φύσει</f>
      <l i="18626">
        <l1 o="n--s---fd-">φύσις</l1>
      </l>
    </t>
    <t p="1" n="154" a="[1]" o="a-p---mn-" u="12">
      <f>πολύσπερμοι</f>
      <l i="396365"/>
    </t>
    <t p="1" n="155" a="[6]" o="u--------" u="13" join="b">
      <f>.</f>
      <l>
        <l2>.</l2>
      </l>
    </t>
  </s>
  <s n="10">
    <t p="1" n="156" a="[1]" o="c--------" u="1">
      <f>ἀλλὰ</f>
      <l>
        <l2>ἀλλά</l2>
      </l>
    </t>
    <t p="1" n="157" a="[8]" o="d--------" u="2">
      <f>καὶ</f>
      <l i="13">
        <l1 o="d---------">καί</l1>
      </l>
    </t>
    <t p="1" n="158" a="[1]" o="v3spia---" u="3">
      <f>θερμαίνει</f>
      <l i="235821">
        <l1 o="v-3spia---">θερμαίνω</l1>
      </l>
    </t>
    <t p="1" n="159" a="[3]" o="l-s---na-" u="4">
      <f>τὸ</f>
      <l i="254">
        <l2>ὁ</l2>
      </l>
    </t>
    <t p="1" n="160" a="[2]" o="n-s---na-" u="5">
      <f>σῶμα</f>
      <l i="16074">
        <l1 o="n--s---na-">σῶμα</l1>
      </l>
    </t>
    <t p="1" n="161" a="[3]" o="l-p---md-" u="6">
      <f>τοῖς</f>
      <l i="1780">
        <l2>ὁ</l2>
      </l>
    </t>
    <t p="1" n="162" a="[1]" o="v-srpefa-" u="7">
      <f>ἐῤῥωμένην</f>
      <l i="425206"/>
    </t>
    <t p="1" n="163" a="[2]" o="v-pppamd-" u="8">
      <f>ἔχουσι</f>
      <l i="26665">
        <l1 o="v--pppamd-">ἔχω</l1>
      </l>
    </t>
    <t p="1" n="164" a="[3]" o="l-s---fa-" u="9">
      <f>τὴν</f>
      <l>
        <l2>ὁ</l2>
      </l>
    </t>
    <t p="1" n="165" a="[2]" o="n-s---fa-" u="10">
      <f>δύναμιν</f>
      <l i="15592">
        <l1 o="n--s---fa-">δύναμις</l1>
      </l>
    </t>
    <t p="1" n="166" a="[1]" o="l-s---fn-" u="11">
      <f>ἡ</f>
      <l i="1317">
        <l2>ὁ</l2>
      </l>
    </t>
    <t p="1" n="167" a="[1]" o="n-s---fn-" u="12">
      <f>λαγνεία</f>
      <l i="425207">
        <l1 o="n--s---fn-">λαγνεία</l1>
      </l>
    </t>
    <t p="1" n="168" a="[13]" o="u--------" u="13" join="b">
      <f>,</f>
      <l>
        <l2>,</l2>
      </l>
    </t>
    <t p="1" n="169" a="[4]" o="l-p---md-" u="14">
      <f>τοῖς</f>
      <l i="1780">
        <l2>ὁ</l2>
      </l>
    </t>
    <t p="1" n="170" a="[6]" o="g--------" u="15">
      <f>δὲ</f>
      <l>
        <l1 o="g---------">δέ</l1>
      </l>
    </t>
    <t p="1" n="171" a="[1]" o="a-p---md-" u="16">
      <f>ἀσθενέσιν</f>
      <l i="209042">
        <l1 o="a--p---md-">ἀσθενής</l1>
      </l>
    </t>
    <t p="1" n="172" a="[1]" o="r--------" u="17">
      <f>ἐν</f>
      <l>
        <l2>ἐν</l2>
      </l>
    </t>
    <t p="1" n="173" a="[5]" o="g--------" u="18">
      <f>μὲν</f>
      <l>
        <l1 o="g---------">μέν</l1>
      </l>
    </t>
    <t p="1" n="174" a="[4]" o="d--------" u="19">
      <f>τῷ</f>
      <l i="454">
        <l1 o="d---------">τῷ</l1>
      </l>
    </t>
    <t p="1" n="175" a="[1]" o="d--------" u="20">
      <f>παραχρῆμα</f>
      <l i="16215">
        <l1 o="d---------">παραχρῆμα</l1>
      </l>
    </t>
    <t p="1" n="176" a="[2]" o="v3spia---" u="21">
      <f>θερμαίνει</f>
      <l i="235821">
        <l1 o="v-3spia---">θερμαίνω</l1>
      </l>
    </t>
    <t p="1" n="177" a="[14]" o="u--------" u="22" join="b">
      <f>,</f>
      <l>
        <l2>,</l2>
      </l>
    </t>
    <t p="1" n="178" a="[1]" o="v3spia---" u="23">
      <f>ψύχει</f>
      <l i="78132">
        <l1 o="v-3spia---">ψύχω</l1>
      </l>
    </t>
    <t p="1" n="179" a="[7]" o="g--------" u="24">
      <f>δὲ</f>
      <l>
        <l1 o="g---------">δέ</l1>
      </l>
    </t>
    <t p="1" n="180" a="[1]" o="r--------" u="25">
      <f>μετὰ</f>
      <l>
        <l2>μετά</l2>
      </l>
    </t>
    <t p="1" n="181" a="[1]" o="p-p---na-" u="26">
      <f>ταῦτα</f>
      <l i="15971">
        <l1 o="pd-p---na-">οὗτος</l1>
      </l>
    </t>
    <t p="1" n="182" a="[1]" o="d--------" u="27">
      <f>γενναίως</f>
      <l i="22589">
        <l1 o="d---------">γενναῖος</l1>
      </l>
    </t>
    <t p="1" n="183" a="[7]" o="u--------" u="28" join="b">
      <f>.</f>
      <l>
        <l2>.</l2>
      </l>
    </t>
  </s>
  <s n="11">
    <t p="1" n="184" a="[1]" o="a-p---mn-" u="1">
      <f>ἔνιοι</f>
      <l i="45321">
        <l1 o="a--p---mn-">ἔνιοι</l1>
      </l>
    </t>
    <t p="1" n="185" a="[6]" o="g--------" u="2">
      <f>μὲν</f>
      <l>
        <l1 o="g---------">μέν</l1>
      </l>
    </t>
    <t p="1" n="186" a="[2]" o="g--------" u="3">
      <f>οὖν</f>
      <l>
        <l1 o="g---------">οὖν</l1>
      </l>
    </t>
    <t p="1" n="187" a="[1]" o="d--------" u="4">
      <f>εὐθέως</f>
      <l i="29255">
        <l1 o="d---------">εὐθύς</l1>
        <l2>εὐθέως</l2>
      </l>
    </t>
    <t p="1" n="188" a="[2]" o="r--------" u="5">
      <f>ἐπὶ</f>
      <l>
        <l2>ἐπί</l2>
      </l>
    </t>
    <t p="1" n="189" a="[2]" o="l-p---fd-" u="6">
      <f>ταῖς</f>
      <l i="12710">
        <l2>ὁ</l2>
      </l>
    </t>
    <t p="1" n="190" a="[1]" o="n-p---fd-" u="7">
      <f>συνουσίαις</f>
      <l i="58546">
        <l1 o="n--p---fd-">συνουσία</l1>
      </l>
    </t>
    <t p="1" n="191" a="[3]" o="r--------" u="8">
      <f>ἀπὸ</f>
      <l>
        <l2>ἀπό</l2>
      </l>
    </t>
    <t p="1" n="192" a="[1]" o="n-s---fg-" u="9">
      <f>νεότητος</f>
      <l i="6396">
        <l1 o="n--s---fg-">νεότης</l1>
      </l>
    </t>
    <t p="1" n="193" a="[1]" o="a-p---mn-" u="10">
      <f>ἀσθενεῖς</f>
      <l i="17046">
        <l1 o="a--p---mn-">ἀσθενής</l1>
      </l>
    </t>
    <t p="1" n="194" a="[1]" o="v3ppie---" u="11">
      <f>γίνονται</f>
      <l i="72056">
        <l2>γίγνομαι</l2>
      </l>
    </t>
    <t p="1" n="195" a="[15]" o="u--------" u="12" join="b">
      <f>,</f>
      <l>
        <l2>,</l2>
      </l>
    </t>
    <t p="1" n="196" a="[1]" o="p-p---mn-" u="13">
      <f>τινὲς</f>
      <l i="15382"/>
    </t>
    <t p="1" n="197" a="[8]" o="g--------" u="14">
      <f>δὲ</f>
      <l>
        <l1 o="g---------">δέ</l1>
      </l>
    </t>
    <t p="1" n="198" a="[16]" o="u--------" u="15" join="b">
      <f>,</f>
      <l>
        <l2>,</l2>
      </l>
    </t>
    <t p="1" n="199" a="[2]" o="c--------" u="16">
      <f>εἰ</f>
      <l i="751">
        <l1 o="c---------">εἰ</l1>
      </l>
    </t>
    <t p="1" n="200" a="[1]" o="d--------" u="17">
      <f>μὴ</f>
      <l i="2166">
        <l1 o="d---------">μή</l1>
      </l>
    </t>
    <t p="1" n="201" a="[1]" o="d--------" u="18">
      <f>συνεχῶς</f>
      <l i="50815">
        <l1 o="d---------">συνεχής</l1>
      </l>
    </t>
    <t p="1" n="202" a="[1]" o="v3ppie---" u="19">
      <f>χρῶνται</f>
      <l i="16109">
        <l1 o="v-3ppie---">χράω2</l1>
        <l2>χράομαι</l2>
        <l2>χραύω</l2>
        <l2>χράω</l2>
      </l>
    </t>
    <t p="1" n="203" a="[17]" o="u--------" u="20" join="b">
      <f>,</f>
      <l>
        <l2>,</l2>
      </l>
    </t>
    <t p="1" n="204" a="[1]" o="v3ppie---" u="21">
      <f>βαρύνονται</f>
      <l i="286867">
        <l1 o="v-3ppie---">βαρύνω</l1>
      </l>
    </t>
    <t p="1" n="205" a="[4]" o="l-s---fa-" u="22">
      <f>τὴν</f>
      <l>
        <l2>ὁ</l2>
      </l>
    </t>
    <t p="1" n="206" a="[1]" o="n-s---fa-" u="23">
      <f>κεφαλὴν</f>
      <l i="11850">
        <l1 o="n--s---fa-">κεφαλή</l1>
      </l>
    </t>
    <t p="1" n="207" a="[18]" o="u--------" u="24" join="b">
      <f>,</f>
      <l>
        <l2>,</l2>
      </l>
    </t>
    <t p="1" n="208" a="[1]" o="a-p---fa-" u="25">
      <f>ἀσώδεις</f>
      <l i="425208"/>
    </t>
    <t p="1" n="209" a="[1]" o="g--------" u="26">
      <f>τε</f>
      <l i="122">
        <l1 o="g---------">τε</l1>
      </l>
    </t>
    <t p="1" n="210" a="[9]" o="c--------" u="27">
      <f>καὶ</f>
      <l i="123">
        <l1 o="c---------">καί</l1>
      </l>
    </t>
    <t p="1" n="211" a="[1]" o="a-p---fa-" u="28">
      <f>πυρετώδεις</f>
      <l i="425209"/>
    </t>
    <t p="1" n="212" a="[2]" o="v3ppie---" u="29">
      <f>γίνονται</f>
      <l i="72056">
        <l2>γίγνομαι</l2>
      </l>
    </t>
    <t p="1" n="213" a="[19]" o="u--------" u="30" join="b">
      <f>,</f>
      <l>
        <l2>,</l2>
      </l>
    </t>
    <t p="1" n="214" a="[10]" o="d--------" u="31">
      <f>καὶ</f>
      <l i="13">
        <l1 o="d---------">καί</l1>
      </l>
    </t>
    <t p="1" n="215" a="[1]" o="a-s---nac" u="32">
      <f>χεῖρον</f>
      <l i="17353">
        <l1 o="a--s---nac">χείρων</l1>
      </l>
    </t>
    <t p="1" n="216" a="[1]" o="v3ppie---" u="33">
      <f>ὀρέγονται</f>
      <l i="211936">
        <l1 o="v-3ppie---">ὀρέγω</l1>
      </l>
    </t>
    <t p="1" n="217" a="[20]" o="u--------" u="34" join="b">
      <f>,</f>
      <l>
        <l2>,</l2>
      </l>
    </t>
    <t p="1" n="218" a="[11]" o="d--------" u="35">
      <f>καὶ</f>
      <l i="13">
        <l1 o="d---------">καί</l1>
      </l>
    </t>
    <t p="1" n="219" a="[1]" o="a-s---nac" u="36">
      <f>ἧττον</f>
      <l i="46752">
        <l1 o="a--s---nac">ἥσσων</l1>
      </l>
    </t>
    <t p="1" n="220" a="[1]" o="v3ppia---" u="37">
      <f>πέττουσι</f>
      <l i="197337">
        <l1 o="v-3ppia---">πέσσω</l1>
      </l>
    </t>
    <t p="1" n="221" a="[8]" o="u--------" u="38" join="b">
      <f>.</f>
      <l>
        <l2>.</l2>
      </l>
    </t>
  </s>
  <s n="12">
    <t p="1" n="222" a="[1]" o="a-s---fg-" u="1">
      <f>τοιαύτης</f>
      <l i="18361">
        <l2>τοιοῦτος</l2>
      </l>
    </t>
    <t p="1" n="223" a="[1]" o="g--------" u="2">
      <f>γοῦν</f>
      <l>
        <l1 o="g---------">γοῦν</l1>
      </l>
    </t>
    <t p="1" n="224" a="[1]" o="a-p---ma-" u="3">
      <f>ἐνίους</f>
      <l i="46919">
        <l1 o="a--p---ma-">ἔνιοι</l1>
      </l>
    </t>
    <t p="1" n="225" a="[1]" o="v-pppama-" u="4">
      <f>ὄντας</f>
      <l i="16942">
        <l1 o="vc-pppama-">εἰμί</l1>
      </l>
    </t>
    <t p="1" n="226" a="[1]" o="n-s---fg-" u="5">
      <f>φύσεως</f>
      <l i="20811">
        <l1 o="n--s---fg-">φύσις</l1>
      </l>
    </t>
    <t p="1" n="227" a="[21]" o="u--------" u="6" join="b">
      <f>,</f>
      <l>
        <l2>,</l2>
      </l>
    </t>
    <t p="1" n="228" a="[1]" o="i--------" u="7">
      <f>εἶτ’</f>
      <l i="397922"/>
    </t>
    <t p="1" n="229" a="[1]" o="a-p---mn-" u="8">
      <f>ἐγκρατεῖς</f>
      <l i="32145">
        <l1 o="a--p---mn-">ἐγκρατής</l1>
      </l>
    </t>
    <t p="1" n="230" a="[1]" o="a-s---mnc" u="9">
      <f>ἀφροδισίων</f>
      <l i="425210"/>
    </t>
    <t p="1" n="231" a="[2]" o="n-s---fg-" u="10">
      <f>χρήσεως</f>
      <l i="82728">
        <l1 o="n--s---fg-">χρῆσις</l1>
      </l>
    </t>
    <t p="1" n="232" a="[1]" o="v-papmma-" u="11">
      <f>γενομένους</f>
      <l i="18597">
        <l1 o="v--papmma-">γίγνομαι</l1>
      </l>
    </t>
    <t p="1" n="233" a="[22]" o="u--------" u="12" join="b">
      <f>,</f>
      <l>
        <l2>,</l2>
      </l>
    </t>
    <t p="1" n="234" a="[1]" o="a-p---fa-" u="13">
      <f>ναρκώδεις</f>
      <l i="425211"/>
    </t>
    <t p="1" n="235" a="[2]" o="g--------" u="14">
      <f>τε</f>
      <l i="122">
        <l1 o="g---------">τε</l1>
      </l>
    </t>
    <t p="1" n="236" a="[12]" o="c--------" u="15">
      <f>καὶ</f>
      <l i="123">
        <l1 o="c---------">καί</l1>
      </l>
    </t>
    <t p="1" n="237" a="[1]" o="a-p---ma-" u="16">
      <f>δυσκινήτους</f>
      <l i="425212"/>
    </t>
    <t p="1" n="238" a="[1]" o="v1pasa---" u="17">
      <f>ἔγνωμεν</f>
      <l i="425213"/>
    </t>
    <t p="1" n="239" a="[1]" o="v-pappma-" u="18">
      <f>ἀποτελεσθέντας</f>
      <l i="133556">
        <l1 o="v--pappma-">ἀποτελέω</l1>
      </l>
    </t>
    <t p="1" n="240" a="[23]" o="u--------" u="19" join="b">
      <f>,</f>
      <l>
        <l2>,</l2>
      </l>
    </t>
    <t p="1" n="241" a="[2]" o="a-p---ma-" u="20">
      <f>ἐνίους</f>
      <l i="46919">
        <l1 o="a--p---ma-">ἔνιοι</l1>
      </l>
    </t>
    <t p="1" n="242" a="[9]" o="g--------" u="21">
      <f>δὲ</f>
      <l>
        <l1 o="g---------">δέ</l1>
      </l>
    </t>
    <t p="1" n="243" a="[13]" o="d--------" u="22">
      <f>καὶ</f>
      <l i="13">
        <l1 o="d---------">καί</l1>
      </l>
    </t>
    <t p="1" n="244" a="[1]" o="n-p---ma-" u="23">
      <f>σκυθρωποὺς</f>
      <l i="425214"/>
    </t>
    <t p="1" n="245" a="[1]" o="d--------" u="24">
      <f>ἀλόγως</f>
      <l i="23523">
        <l1 o="d---------">ἄλογος</l1>
      </l>
    </t>
    <t p="1" n="246" a="[14]" o="d--------" u="25">
      <f>καὶ</f>
      <l i="13">
        <l1 o="d---------">καί</l1>
      </l>
    </t>
    <t p="1" n="247" a="[1]" o="n-p---ma-" u="26">
      <f>δυσέλπιδας</f>
      <l i="68318"/>
    </t>
    <t p="1" n="248" a="[1]" o="d--------" u="27">
      <f>ὁμοίως</f>
      <l i="15228">
        <l1 o="d---------">ὅμοιος</l1>
      </l>
    </t>
    <t p="1" n="249" a="[5]" o="l-p---md-" u="28">
      <f>τοῖς</f>
      <l i="1780">
        <l2>ὁ</l2>
      </l>
    </t>
    <t p="1" n="250" a="[1]" o="a-p---md-" u="29">
      <f>μελαγχολικοῖς</f>
      <l i="425215"/>
    </t>
    <t p="1" n="251" a="[4]" o="u--------" u="30" join="b">
      <f>·</f>
      <l>
        <l2>·</l2>
      </l>
    </t>
  </s>
  <s n="13">
    <t p="1" n="252" a="[2]" o="p-p---na-" u="1">
      <f>ταῦτα</f>
      <l i="15971">
        <l1 o="pd-p---na-">οὗτος</l1>
      </l>
    </t>
    <t p="1" n="253" a="[10]" o="g--------" u="2">
      <f>δὲ</f>
      <l>
        <l1 o="g---------">δέ</l1>
      </l>
    </t>
    <t p="1" n="254" a="[1]" o="v-pppenn-" u="3">
      <f>παυόμενα</f>
      <l i="425216"/>
    </t>
    <t p="1" n="255" a="[1]" o="d--------" u="4">
      <f>ταχέως</f>
      <l i="18433">
        <l1 o="d---------">ταχύς</l1>
        <l2>ταχέως</l2>
      </l>
    </t>
    <t p="1" n="256" a="[3]" o="r--------" u="5">
      <f>ἐπὶ</f>
      <l>
        <l2>ἐπί</l2>
      </l>
    </t>
    <t p="1" n="257" a="[3]" o="l-p---fd-" u="6">
      <f>ταῖς</f>
      <l i="12710">
        <l2>ὁ</l2>
      </l>
    </t>
    <t p="1" n="258" a="[2]" o="l-p---mg-" u="7">
      <f>τῶν</f>
      <l i="1221">
        <l2>ὁ</l2>
      </l>
    </t>
    <t p="1" n="259" a="[2]" o="a-p---ng-" u="8">
      <f>ἀφροδισίων</f>
      <l i="73099">
        <l1 o="ae-p---ng-">Ἀφροδίσιος</l1>
      </l>
    </t>
    <t p="1" n="260" a="[1]" o="n-p---fd-" u="9">
      <f>χρήσεσι</f>
      <l i="396712"/>
    </t>
    <t p="1" n="261" a="[9]" o="u--------" u="10" join="b">
      <f>.</f>
      <l>
        <l2>.</l2>
      </l>
    </t>
  </s>
  <s n="14">
    <t p="1" n="262" a="[1]" o="v1sria---" u="1">
      <f>ταῦτ’</f>
      <l i="397603"/>
    </t>
    <t p="1" n="263" a="[1]" o="v-sppemd-" u="2">
      <f>ἀναλογιζομένῳ</f>
      <l i="425217"/>
    </t>
    <t p="1" n="264" a="[1]" o="p-s---md-" u="3">
      <f>μοι</f>
      <l i="1341"/>
    </t>
    <t p="1" n="265" a="[1]" o="d--------" u="4">
      <f>μεγάλως</f>
      <l i="86806">
        <l1 o="d---------">μέγας</l1>
        <l2>μεγάλως</l2>
      </l>
    </t>
    <t p="1" n="266" a="[1]" o="v3spie---" u="5">
      <f>φαίνεται</f>
      <l i="7342">
        <l1 o="v-3spie---">φαίνω</l1>
      </l>
    </t>
    <t p="1" n="267" a="[1]" o="v--pna---" u="6">
      <f>βλάπτειν</f>
      <l i="17322">
        <l1 o="v---pna---">βλάπτω</l1>
      </l>
    </t>
    <t p="1" n="268" a="[2]" o="l-s---fn-" u="7">
      <f>ἡ</f>
      <l i="1317">
        <l2>ὁ</l2>
      </l>
    </t>
    <t p="1" n="269" a="[1]" o="l-s---ng-" u="8">
      <f>τοῦ</f>
      <l i="6308">
        <l2>ὁ</l2>
      </l>
    </t>
    <t p="1" n="270" a="[1]" o="n-s---ng-" u="9">
      <f>σπέρματος</f>
      <l i="50167">
        <l1 o="n--s---ng-">σπέρμα</l1>
      </l>
    </t>
    <t p="1" n="271" a="[1]" o="n-s---fn-" u="10">
      <f>ἐπίσχεσις</f>
      <l i="21896">
        <l1 o="n--s---fn-">ἐπίσχεσις</l1>
      </l>
    </t>
    <t p="1" n="272" a="[24]" o="u--------" u="11" join="b">
      <f>,</f>
      <l>
        <l2>,</l2>
      </l>
    </t>
    <t p="1" n="273" a="[1]" o="r--------" u="12">
      <f>ἐφ’</f>
      <l>
        <l2>ἐπί</l2>
      </l>
    </t>
    <t p="1" n="274" a="[1]" o="p-p---mg-" u="13">
      <f>ὧν</f>
      <l i="5594">
        <l1 o="pr-p---mg-">ὅς</l1>
        <l1 o="ps-p---mg-">ὅς2</l1>
      </l>
    </t>
    <t p="1" n="275" a="[1]" o="v3piie---" u="14">
      <f>αὐτό</f>
      <l i="397048"/>
    </t>
    <t p="1" n="276" a="[3]" o="d--------" u="15">
      <f>τε</f>
      <l>
        <l2>τε</l2>
      </l>
    </t>
    <t p="1" n="277" a="[2]" o="n-s---fd-" u="16">
      <f>φύσει</f>
      <l i="18626">
        <l1 o="n--s---fd-">φύσις</l1>
      </l>
    </t>
    <t p="1" n="278" a="[1]" o="a-s---nac" u="17">
      <f>κακοχυμότερον</f>
      <l i="425218"/>
    </t>
    <t p="1" n="279" a="[15]" o="d--------" u="18">
      <f>καὶ</f>
      <l i="13">
        <l1 o="d---------">καί</l1>
      </l>
    </t>
    <t p="1" n="280" a="[1]" o="a-s---nac" u="19">
      <f>πλέον</f>
      <l i="7416">
        <l1 o="a--s---nac">πολύς</l1>
        <l2>πλείων</l2>
      </l>
    </t>
    <t p="1" n="281" a="[25]" o="u--------" u="20" join="b">
      <f>,</f>
      <l>
        <l2>,</l2>
      </l>
    </t>
    <t p="1" n="282" a="[1]" o="a-s---mn-" u="21">
      <f>ἀργότερός</f>
      <l i="425219"/>
    </t>
    <t p="1" n="283" a="[4]" o="g--------" u="22">
      <f>τε</f>
      <l i="122">
        <l1 o="g---------">τε</l1>
      </l>
    </t>
    <t p="1" n="284" a="[2]" o="l-s---mn-" u="23">
      <f>ὁ</f>
      <l i="394">
        <l2>ὁ</l2>
      </l>
    </t>
    <t p="1" n="285" a="[1]" o="n-s---mn-" u="24">
      <f>βίος</f>
      <l i="22714">
        <l1 o="n--s---mn-">βίος</l1>
        <l2>βιός</l2>
      </l>
    </t>
    <t p="1" n="286" a="[26]" o="u--------" u="25" join="b">
      <f>,</f>
      <l>
        <l2>,</l2>
      </l>
    </t>
    <t p="1" n="287" a="[16]" o="d--------" u="26">
      <f>καὶ</f>
      <l i="13">
        <l1 o="d---------">καί</l1>
      </l>
    </t>
    <t p="1" n="288" a="[3]" o="l-p---ng-" u="27">
      <f>τῶν</f>
      <l i="15254">
        <l2>ὁ</l2>
      </l>
    </t>
    <t p="1" n="289" a="[3]" o="a-p---ng-" u="28">
      <f>ἀφροδισίων</f>
      <l i="73099">
        <l1 o="ae-p---ng-">Ἀφροδίσιος</l1>
      </l>
    </t>
    <t p="1" n="290" a="[7]" o="g--------" u="29">
      <f>μὲν</f>
      <l>
        <l1 o="g---------">μέν</l1>
      </l>
    </t>
    <t p="1" n="291" a="[3]" o="l-s---fn-" u="30">
      <f>ἡ</f>
      <l i="1317">
        <l2>ὁ</l2>
      </l>
    </t>
    <t p="1" n="292" a="[2]" o="n-s---fn-" u="31">
      <f>χρῆσις</f>
      <l i="35976">
        <l1 o="n--s---fn-">χρῆσις</l1>
      </l>
    </t>
    <t p="1" n="293" a="[1]" o="a-s---na-" u="32">
      <f>πρότερον</f>
      <l i="15256">
        <l2>πρότερος</l2>
      </l>
    </t>
    <t p="1" n="294" a="[8]" o="g--------" u="33">
      <f>μὲν</f>
      <l>
        <l1 o="g---------">μέν</l1>
      </l>
    </t>
    <t p="1" n="295" a="[1]" o="n-s---fn-" u="34">
      <f>ἱκανὴ</f>
      <l i="298842"/>
    </t>
    <t p="1" n="296" a="[1]" o="d--------" u="35">
      <f>πάνυ</f>
      <l i="15266">
        <l1 o="d---------">πάνυ</l1>
      </l>
    </t>
    <t p="1" n="297" a="[27]" o="u--------" u="36" join="b">
      <f>,</f>
      <l>
        <l2>,</l2>
      </l>
    </t>
    <t p="1" n="298" a="[2]" o="r--------" u="37">
      <f>μετὰ</f>
      <l>
        <l2>μετά</l2>
      </l>
    </t>
    <t p="1" n="299" a="[3]" o="p-p---na-" u="38">
      <f>ταῦτα</f>
      <l i="15971">
        <l1 o="pd-p---na-">οὗτος</l1>
      </l>
    </t>
    <t p="1" n="300" a="[11]" o="g--------" u="39">
      <f>δὲ</f>
      <l>
        <l1 o="g---------">δέ</l1>
      </l>
    </t>
    <t p="1" n="301" a="[1]" o="d--------" u="40">
      <f>ἀθρόως</f>
      <l i="62283">
        <l1 o="d---------">ἀθρόος</l1>
      </l>
    </t>
    <t p="1" n="302" a="[2]" o="a-p---mn-" u="41">
      <f>ἐγκρατεῖς</f>
      <l i="32145">
        <l1 o="a--p---mn-">ἐγκρατής</l1>
      </l>
    </t>
    <t p="1" n="303" a="[1]" o="v3paip---" u="42">
      <f>ἐγενήθησαν</f>
      <l i="200955">
        <l1 o="v-3paip---">γίγνομαι</l1>
      </l>
    </t>
    <t p="1" n="304" a="[28]" o="u--------" u="43" join="b">
      <f>,</f>
      <l>
        <l2>,</l2>
      </l>
    </t>
    <t p="1" n="305" a="[1]" o="a-p---mn-" u="44">
      <f>ἰσχυροί</f>
      <l i="208863">
        <l1 o="a--p---mn-">ἰσχυρός</l1>
      </l>
    </t>
    <t p="1" n="306" a="[5]" o="g--------" u="45">
      <f>τε</f>
      <l i="122">
        <l1 o="g---------">τε</l1>
      </l>
    </t>
    <t p="1" n="307" a="[17]" o="d--------" u="46">
      <f>καὶ</f>
      <l i="13">
        <l1 o="d---------">καί</l1>
      </l>
    </t>
    <t p="1" n="308" a="[1]" o="a-p---mn-" u="47">
      <f>νέοι</f>
      <l i="1554">
        <l1 o="a--p---mn-">νέος</l1>
      </l>
    </t>
    <t p="1" n="309" a="[10]" o="u--------" u="48" join="b">
      <f>.</f>
      <l>
        <l2>.</l2>
      </l>
    </t>
  </s>
  <s n="15">
    <t p="1" n="310" a="[1]" o="p-p---md-" u="1">
      <f>τούτοις</f>
      <l i="17891">
        <l1 o="pd-p---md-">οὗτος</l1>
      </l>
    </t>
    <t p="1" n="311" a="[4]" o="l-s---fn-" u="2">
      <f>ἡ</f>
      <l i="1317">
        <l2>ὁ</l2>
      </l>
    </t>
    <t p="1" n="312" a="[2]" o="l-s---ng-" u="3">
      <f>τοῦ</f>
      <l i="6308">
        <l2>ὁ</l2>
      </l>
    </t>
    <t p="1" n="313" a="[1]" o="n-s---ng-" u="4">
      <f>σώματος</f>
      <l i="22937">
        <l1 o="n--s---ng-">σῶμα</l1>
      </l>
    </t>
    <t p="1" n="314" a="[1]" o="n-s---fn-" u="5">
      <f>ἕξις</f>
      <l i="220797">
        <l1 o="n--s---fn-">ἕξις</l1>
      </l>
    </t>
    <t p="1" n="315" a="[2]" o="r--------" u="6">
      <f>εἰς</f>
      <l>
        <l2>εἰς</l2>
      </l>
    </t>
    <t p="1" n="316" a="[1]" o="n-s---fa-" u="7">
      <f>ἀραιότητα</f>
      <l i="425220">
        <l1 o="n--s---fa-">ἀραιότης</l1>
      </l>
    </t>
    <t p="1" n="317" a="[2]" o="a-s---nac" u="8">
      <f>πλέον</f>
      <l i="7416">
        <l1 o="a--s---nac">πολύς</l1>
        <l2>πλείων</l2>
      </l>
    </t>
    <t p="1" n="318" a="[1]" o="c--------" u="9">
      <f>ἤπερ</f>
      <l i="61442">
        <l1 o="c---------">ἤ</l1>
        <l2>ἠπειρωτικός</l2>
      </l>
    </t>
    <t p="1" n="319" a="[5]" o="l-s---fn-" u="10">
      <f>ἡ</f>
      <l i="1317">
        <l2>ὁ</l2>
      </l>
    </t>
    <t p="1" n="320" a="[1]" o="n-s---fn-" u="11">
      <f>δύναμις</f>
      <l i="16025">
        <l1 o="n--s---fn-">δύναμις</l1>
      </l>
    </t>
    <t p="1" n="321" a="[3]" o="r--------" u="12">
      <f>εἰς</f>
      <l>
        <l2>εἰς</l2>
      </l>
    </t>
    <t p="1" n="322" a="[2]" o="n-s---fa-" u="13">
      <f>ἀῤῥωστίαν</f>
      <l i="412870"/>
    </t>
    <t p="1" n="323" a="[1]" o="v3spie---" u="14">
      <f>ἀλλοιοῦται</f>
      <l i="78949">
        <l1 o="v-3spie---">ἀλλοιόω</l1>
      </l>
    </t>
    <t p="1" n="324" a="[5]" o="u--------" u="15" join="b">
      <f>·</f>
      <l>
        <l2>·</l2>
      </l>
    </t>
  </s>
  <s n="16">
    <t p="1" n="325" a="[1]" o="d--------" u="1">
      <f>καί</f>
      <l i="656">
        <l1 o="d---------">καί</l1>
      </l>
    </t>
    <t p="1" n="326" a="[1]" o="p-s---mn-" u="2">
      <f>τις</f>
      <l i="963">
        <l2>τις</l2>
      </l>
    </t>
    <t p="1" n="327" a="[1]" o="n-s---fn-" u="3">
      <f>ἐπανόρθωσις</f>
      <l i="366313">
        <l1 o="n--s---fn-">ἐπανόρθωσις</l1>
      </l>
    </t>
    <t p="1" n="328" a="[1]" o="r--------" u="4">
      <f>διὰ</f>
      <l>
        <l2>διά</l2>
      </l>
    </t>
    <t p="1" n="329" a="[4]" o="l-p---mg-" u="5">
      <f>τῶν</f>
      <l i="1221">
        <l2>ὁ</l2>
      </l>
    </t>
    <t p="1" n="330" a="[1]" o="v-pppamg-" u="6">
      <f>συναγόντων</f>
      <l i="215026">
        <l1 o="v--pppamg-">συνάγω</l1>
      </l>
    </t>
    <t p="1" n="331" a="[18]" o="d--------" u="7">
      <f>καὶ</f>
      <l i="13">
        <l1 o="d---------">καί</l1>
      </l>
    </t>
    <t p="1" n="332" a="[1]" o="v-pppamg-" u="8">
      <f>σφιγγόντων</f>
      <l i="425221"/>
    </t>
    <t p="1" n="333" a="[1]" o="v3spie---" u="9">
      <f>γίνεται</f>
      <l i="50207">
        <l2>γίγνομαι</l2>
      </l>
    </t>
    <t p="1" n="334" a="[1]" o="p-p---md-" u="10">
      <f>αὐτοῖς</f>
      <l i="4850">
        <l1 o="pp-p---md-">αὐτός</l1>
      </l>
    </t>
    <t p="1" n="335" a="[29]" o="u--------" u="11" join="b">
      <f>,</f>
      <l>
        <l2>,</l2>
      </l>
    </t>
    <t p="1" n="336" a="[1]" o="a-s---nn-" u="12">
      <f>ὁποῖόν</f>
      <l i="82781"/>
    </t>
    <t p="1" n="337" a="[2]" o="v3spia---" u="13">
      <f>ἐστι</f>
      <l i="9261">
        <l1 o="vc3spia---">εἰμί</l1>
      </l>
    </t>
    <t p="1" n="338" a="[1]" o="a-s---nn-" u="14">
      <f>παρασκευαστικὸν</f>
      <l i="219201">
        <l1 o="a--s---nn-">παρασκευαστικός</l1>
      </l>
    </t>
    <t p="1" n="339" a="[1]" o="n-s---nn-" u="15">
      <f>γυμνάσιον</f>
      <l i="55837">
        <l1 o="n--s---nn-">γυμνάσιον</l1>
      </l>
    </t>
    <t p="1" n="340" a="[11]" o="u--------" u="16" join="b">
      <f>.</f>
      <l>
        <l2>.</l2>
      </l>
    </t>
  </s>
  <s n="17">
    <t p="1" n="341" a="[3]" o="c--------" u="1">
      <f>εἰ</f>
      <l i="751">
        <l1 o="c---------">εἰ</l1>
      </l>
    </t>
    <t p="1" n="342" a="[12]" o="g--------" u="2">
      <f>δὲ</f>
      <l>
        <l1 o="g---------">δέ</l1>
      </l>
    </t>
    <t p="1" n="343" a="[1]" o="g--------" u="3">
      <f>δὴ</f>
      <l>
        <l1 o="g---------">δή</l1>
      </l>
    </t>
    <t p="1" n="344" a="[19]" o="d--------" u="4">
      <f>καὶ</f>
      <l i="13">
        <l1 o="d---------">καί</l1>
      </l>
    </t>
    <t p="1" n="345" a="[1]" o="n-s---fn-" u="5">
      <f>ψύξις</f>
      <l i="398624">
        <l1 o="n--s---fn-">ψῦξις</l1>
      </l>
    </t>
    <t p="1" n="346" a="[2]" o="p-s---fn-" u="6">
      <f>τις</f>
      <l i="3691">
        <l2>τις</l2>
      </l>
    </t>
    <t p="1" n="347" a="[4]" o="r--------" u="7">
      <f>ἐπὶ</f>
      <l>
        <l2>ἐπί</l2>
      </l>
    </t>
    <t p="1" n="348" a="[6]" o="l-p---md-" u="8">
      <f>τοῖς</f>
      <l i="1780">
        <l2>ὁ</l2>
      </l>
    </t>
    <t p="1" n="349" a="[2]" o="a-p---md-" u="9">
      <f>ἀφροδισίοις</f>
      <l i="99420">
        <l1 o="ae-p---md-">Ἀφροδίσιος</l1>
      </l>
    </t>
    <t p="1" n="350" a="[1]" o="v3spoe---" u="10">
      <f>ἐγγίγνοιτο</f>
      <l i="425222">
        <l2>ἐγγίγνομαι</l2>
      </l>
    </t>
    <t p="1" n="351" a="[30]" o="u--------" u="11" join="b">
      <f>,</f>
      <l>
        <l2>,</l2>
      </l>
    </t>
    <t p="1" n="352" a="[20]" o="d--------" u="12">
      <f>καὶ</f>
      <l i="13">
        <l1 o="d---------">καί</l1>
      </l>
    </t>
    <t p="1" n="353" a="[3]" o="r--------" u="13">
      <f>κατὰ</f>
      <l>
        <l2>κατά</l2>
      </l>
    </t>
    <t p="1" n="354" a="[1]" o="v2ppse---" u="14">
      <f>τοῦτ’</f>
      <l i="398781"/>
    </t>
    <t p="1" n="355" a="[1]" o="g--------" u="15">
      <f>ἂν</f>
      <l>
        <l1 o="gm--------">ἄν</l1>
      </l>
    </t>
    <t p="1" n="356" a="[1]" o="v3spoa---" u="16">
      <f>εἴη</f>
      <l i="5716">
        <l1 o="vc3spoa---">εἰμί</l1>
      </l>
    </t>
    <t p="1" n="357" a="[5]" o="d--------" u="17">
      <f>τῷ</f>
      <l i="454">
        <l1 o="d---------">τῷ</l1>
      </l>
    </t>
    <t p="1" n="358" a="[1]" o="a-s---nd-" u="18">
      <f>παρασκευαστικῷ</f>
      <l i="425223"/>
    </t>
    <t p="1" n="359" a="[1]" o="n-s---nd-" u="19">
      <f>γυμνασίῳ</f>
      <l i="214204">
        <l1 o="n--s---nd-">γυμνάσιον</l1>
      </l>
    </t>
    <t p="1" n="360" a="[1]" o="a-s---nn-" u="20">
      <f>χρηστέον</f>
      <l i="67380">
        <l1 o="a--s---nn-">χράομαι</l1>
        <l2>χρηστέος</l2>
      </l>
    </t>
    <t p="1" n="361" a="[31]" o="u--------" u="21" join="b">
      <f>,</f>
      <l>
        <l2>,</l2>
      </l>
    </t>
    <t p="1" n="362" a="[1]" o="v3siia---" u="22">
      <f>ἐπεγείρει</f>
      <l i="425224"/>
    </t>
    <t p="1" n="363" a="[2]" o="g--------" u="23">
      <f>γὰρ</f>
      <l>
        <l1 o="g---------">γάρ</l1>
      </l>
    </t>
    <t p="1" n="364" a="[5]" o="l-s---fa-" u="24">
      <f>τὴν</f>
      <l>
        <l2>ὁ</l2>
      </l>
    </t>
    <t p="1" n="365" a="[1]" o="n-s---fa-" u="25">
      <f>θερμότητα</f>
      <l i="69985">
        <l1 o="n--s---fa-">θερμότης</l1>
      </l>
    </t>
    <t p="1" n="366" a="[12]" o="u--------" u="26" join="b">
      <f>.</f>
      <l>
        <l2>.</l2>
      </l>
    </t>
  </s>
  <s n="18">
    <t p="1" n="367" a="[3]" o="l-s---fg-" u="1">
      <f>τῆς</f>
      <l i="3017">
        <l2>ὁ</l2>
      </l>
    </t>
    <t p="1" n="368" a="[13]" o="g--------" u="2">
      <f>δὲ</f>
      <l>
        <l1 o="g---------">δέ</l1>
      </l>
    </t>
    <t p="1" n="369" a="[1]" o="n-s---fg-" u="3">
      <f>ὥρας</f>
      <l i="36682">
        <l1 o="n--s---fg-">ὥρα2</l1>
        <l2>ὥρα</l2>
      </l>
    </t>
    <t p="1" n="370" a="[3]" o="l-s---ng-" u="4">
      <f>τοῦ</f>
      <l i="6308">
        <l2>ὁ</l2>
      </l>
    </t>
    <t p="1" n="371" a="[1]" o="n-s---ng-" u="5">
      <f>ἔτους</f>
      <l i="31940">
        <l1 o="n--s---ng-">ἔτος</l1>
      </l>
    </t>
    <t p="1" n="372" a="[1]" o="v-sppafg-" u="6">
      <f>ἐπιτρεπούσης</f>
      <l i="298474">
        <l1 o="v--sppafg-">ἐπιτρέπω</l1>
      </l>
    </t>
    <t p="1" n="373" a="[32]" o="u--------" u="7" join="b">
      <f>,</f>
      <l>
        <l2>,</l2>
      </l>
    </t>
    <t p="1" n="374" a="[1]" o="d--------" u="8">
      <f>οὐδὲ</f>
      <l i="257">
        <l1 o="d---------">οὐδέ</l1>
      </l>
    </t>
    <t p="1" n="375" a="[4]" o="l-s---fg-" u="9">
      <f>τῆς</f>
      <l i="3017">
        <l2>ὁ</l2>
      </l>
    </t>
    <t p="1" n="376" a="[1]" o="n-s---fg-" u="10">
      <f>ψυχρολουσίας</f>
      <l i="425225"/>
    </t>
    <t p="1" n="377" a="[1]" o="a-s---nn-" u="11">
      <f>ἀφεκτέον</f>
      <l i="98134">
        <l1 o="a--s---nn-">ἀπέχω</l1>
        <l2>ἀφεκτέος</l2>
      </l>
    </t>
    <t p="1" n="378" a="[13]" o="u--------" u="12" join="b">
      <f>.</f>
      <l>
        <l2>.</l2>
      </l>
    </t>
  </s>
  <s n="19">
    <t p="1" n="379" a="[1]" o="n-p---nn-" u="1">
      <f>ἐδέσματα</f>
      <l i="425226">
        <l1 o="n--p---nn-">ἔδεσμα</l1>
      </l>
    </t>
    <t p="1" n="380" a="[14]" o="g--------" u="2">
      <f>δὲ</f>
      <l>
        <l1 o="g---------">δέ</l1>
      </l>
    </t>
    <t p="1" n="381" a="[6]" o="d--------" u="3">
      <f>τῷ</f>
      <l i="454">
        <l1 o="d---------">τῷ</l1>
      </l>
    </t>
    <t p="1" n="382" a="[1]" o="n-s---nd-" u="4">
      <f>πλήθει</f>
      <l i="15244">
        <l1 o="n--s---nd-">πλῆθος</l1>
      </l>
    </t>
    <t p="1" n="383" a="[9]" o="g--------" u="5">
      <f>μὲν</f>
      <l>
        <l1 o="g---------">μέν</l1>
      </l>
    </t>
    <t p="1" n="384" a="[1]" o="a-s---fac" u="6">
      <f>ἐλάττω</f>
      <l i="49579">
        <l1 o="a--s---fac">ἐλάσσων</l1>
      </l>
    </t>
    <t p="1" n="385" a="[33]" o="u--------" u="7" join="b">
      <f>,</f>
      <l>
        <l2>,</l2>
      </l>
    </t>
    <t p="1" n="386" a="[1]" o="d--------" u="8">
      <f>τῇ</f>
      <l i="1260">
        <l1 o="dd--------">ὁ</l1>
        <l1 o="dr--------">ὅς</l1>
        <l2>τῇ</l2>
      </l>
    </t>
    <t p="1" n="387" a="[1]" o="n-s---fd-" u="9">
      <f>ποιότητι</f>
      <l i="356434">
        <l1 o="n--s---fd-">ποιότης</l1>
      </l>
    </t>
    <t p="1" n="388" a="[15]" o="g--------" u="10">
      <f>δὲ</f>
      <l>
        <l1 o="g---------">δέ</l1>
      </l>
    </t>
    <t p="1" n="389" a="[21]" o="d--------" u="11">
      <f>καὶ</f>
      <l i="13">
        <l1 o="d---------">καί</l1>
      </l>
    </t>
    <t p="1" n="390" a="[1]" o="a-p---na-" u="12">
      <f>ὑγρότερα</f>
      <l i="396464"/>
    </t>
    <t p="1" n="391" a="[1]" o="a-s---nn-" u="13">
      <f>δοτέον</f>
      <l i="53982">
        <l1 o="a--s---nn-">δίδωμι</l1>
        <l2>δοτέος</l2>
      </l>
    </t>
    <t p="1" n="392" a="[34]" o="u--------" u="14" join="b">
      <f>,</f>
      <l>
        <l2>,</l2>
      </l>
    </t>
    <t p="1" n="393" a="[1]" o="c--------" u="15">
      <f>ἵνα</f>
      <l i="519">
        <l1 o="c---------">ἵνα</l1>
      </l>
    </t>
    <t p="1" n="394" a="[22]" o="d--------" u="16">
      <f>καὶ</f>
      <l i="13">
        <l1 o="d---------">καί</l1>
      </l>
    </t>
    <t p="1" n="395" a="[1]" o="v3sasa---" u="17">
      <f>πέψῃ</f>
      <l i="425227"/>
    </t>
    <t p="1" n="396" a="[1]" o="d--------" u="18">
      <f>καλῶς</f>
      <l i="15384">
        <l1 o="d---------">καλός</l1>
      </l>
    </t>
    <t p="1" n="397" a="[1]" o="p-p---na-" u="19">
      <f>αὐτὰ</f>
      <l i="16346">
        <l1 o="pp-p---na-">αὐτός</l1>
      </l>
    </t>
    <t p="1" n="398" a="[35]" o="u--------" u="20" join="b">
      <f>,</f>
      <l>
        <l2>,</l2>
      </l>
    </t>
    <t p="1" n="399" a="[23]" o="d--------" u="21">
      <f>καὶ</f>
      <l i="13">
        <l1 o="d---------">καί</l1>
      </l>
    </t>
    <t p="1" n="400" a="[6]" o="l-s---fa-" u="22">
      <f>τὴν</f>
      <l>
        <l2>ὁ</l2>
      </l>
    </t>
    <t p="1" n="401" a="[4]" o="a-p---fg-" u="23">
      <f>ἀφροδισίων</f>
      <l i="77538">
        <l1 o="ae-p---fg-">Ἀφροδίσιος</l1>
      </l>
    </t>
    <t p="1" n="402" a="[1]" o="v3sasm---" u="24">
      <f>ἐπανορθώσηται</f>
      <l i="425228"/>
    </t>
    <t p="1" n="403" a="[1]" o="n-s---fa-" u="25">
      <f>ξηρότητα</f>
      <l i="69599">
        <l1 o="n--s---fa-">ξηρότης</l1>
      </l>
    </t>
    <t p="1" n="404" a="[14]" o="u--------" u="26" join="b">
      <f>.</f>
      <l>
        <l2>.</l2>
      </l>
    </t>
  </s>
  <s n="20">
    <t p="1" n="405" a="[1]" o="v3spia---" u="1">
      <f>χρὴ</f>
      <l i="8650">
        <l1 o="v-3spia---">χρή</l1>
      </l>
    </t>
    <t p="1" n="406" a="[16]" o="g--------" u="2">
      <f>δὲ</f>
      <l>
        <l1 o="g---------">δέ</l1>
      </l>
    </t>
    <t p="1" n="407" a="[2]" o="d--------" u="3">
      <f>οὐδὲ</f>
      <l i="257">
        <l1 o="d---------">οὐδέ</l1>
      </l>
    </t>
    <t p="1" n="408" a="[1]" o="a-p---na-" u="4">
      <f>ψυχρότερα</f>
      <l i="70624"/>
    </t>
    <t p="1" n="409" a="[7]" o="l-s---fa-" u="5">
      <f>τὴν</f>
      <l>
        <l2>ὁ</l2>
      </l>
    </t>
    <t p="1" n="410" a="[1]" o="n-s---fa-" u="6">
      <f>κρᾶσιν</f>
      <l i="49411">
        <l1 o="n--s---fa-">κρᾶσις</l1>
      </l>
    </t>
    <t p="1" n="411" a="[36]" o="u--------" u="7" join="b">
      <f>,</f>
      <l>
        <l2>,</l2>
      </l>
    </t>
    <t p="1" n="412" a="[2]" o="c--------" u="8">
      <f>ἀλλὰ</f>
      <l>
        <l2>ἀλλά</l2>
      </l>
    </t>
    <t p="1" n="413" a="[5]" o="l-s---fg-" u="9">
      <f>τῆς</f>
      <l i="3017">
        <l2>ὁ</l2>
      </l>
    </t>
    <t p="1" n="414" a="[1]" o="a-s---fg-" u="10">
      <f>μέσης</f>
      <l i="44392">
        <l1 o="a--s---fg-">μέσος</l1>
      </l>
    </t>
    <t p="1" n="415" a="[1]" o="n-s---fg-" u="11">
      <f>ἰδέας</f>
      <l i="76480">
        <l1 o="n--s---fg-">ἰδέα</l1>
      </l>
    </t>
    <t p="1" n="416" a="[5]" o="l-p---mg-" u="12">
      <f>τῶν</f>
      <l i="1221">
        <l2>ὁ</l2>
      </l>
    </t>
    <t p="1" n="417" a="[1]" o="v-pppamg-" u="13">
      <f>θερμαινόντων</f>
      <l i="396148"/>
    </t>
    <t p="1" n="418" a="[1]" o="v--pna---" u="14">
      <f>ὑπάρχειν</f>
      <l i="21385">
        <l1 o="v---pna---">ὑπάρχω</l1>
      </l>
    </t>
    <t p="1" n="419" a="[1]" o="a-p---na-" u="15">
      <f>αὐτά</f>
      <l i="21174">
        <l1 o="a--p---na-">αὐτός</l1>
      </l>
    </t>
    <t p="1" n="420" a="[15]" o="u--------" u="16" join="b">
      <f>.</f>
      <l>
        <l2>.</l2>
      </l>
    </t>
  </s>
  <s n="21">
    <t p="1" n="421" a="[1]" o="c--------" u="1">
      <f>διότι</f>
      <l i="16324">
        <l1 o="c---------">διότι</l1>
      </l>
    </t>
    <t p="1" n="422" a="[3]" o="g--------" u="2">
      <f>γὰρ</f>
      <l>
        <l1 o="g---------">γάρ</l1>
      </l>
    </t>
    <t p="1" n="423" a="[1]" o="r--------" u="3">
      <f>ἐξ</f>
      <l>
        <l2>ἐκ</l2>
      </l>
    </t>
    <t p="1" n="424" a="[5]" o="a-p---ng-" u="4">
      <f>ἀφροδισίων</f>
      <l i="73099">
        <l1 o="ae-p---ng-">Ἀφροδίσιος</l1>
      </l>
    </t>
    <t p="1" n="425" a="[1]" o="a-s---na-" u="5">
      <f>ἀραιότερον</f>
      <l i="394978"/>
    </t>
    <t p="1" n="426" a="[1]" o="d--------" u="6">
      <f>ἅμα</f>
      <l i="2709">
        <l1 o="d---------">ἅμα</l1>
      </l>
    </t>
    <t p="1" n="427" a="[24]" o="d--------" u="7">
      <f>καὶ</f>
      <l i="13">
        <l1 o="d---------">καί</l1>
      </l>
    </t>
    <t p="1" n="428" a="[1]" o="a-s---nnc" u="8">
      <f>ἀσθενέστερον</f>
      <l i="175795">
        <l1 o="a--s---nnc">ἀσθενής</l1>
      </l>
    </t>
    <t p="1" n="429" a="[37]" o="u--------" u="9" join="b">
      <f>,</f>
      <l>
        <l2>,</l2>
      </l>
    </t>
    <t p="1" n="430" a="[1]" o="a-s---na-" u="10">
      <f>ψυχρότερόν</f>
      <l i="323113"/>
    </t>
    <t p="1" n="431" a="[6]" o="g--------" u="11">
      <f>τε</f>
      <l i="122">
        <l1 o="g---------">τε</l1>
      </l>
    </t>
    <t p="1" n="432" a="[25]" o="c--------" u="12">
      <f>καὶ</f>
      <l i="123">
        <l1 o="c---------">καί</l1>
      </l>
    </t>
    <t p="1" n="433" a="[1]" o="a-s---na-" u="13">
      <f>ξηρότερον</f>
      <l i="396322"/>
    </t>
    <t p="1" n="434" a="[1]" o="v3spie---" u="14">
      <f>ἀποτελεῖται</f>
      <l i="222325">
        <l1 o="v-3spie---">ἀποτελέω</l1>
      </l>
    </t>
    <t p="1" n="435" a="[4]" o="l-s---na-" u="15">
      <f>τὸ</f>
      <l i="254">
        <l2>ὁ</l2>
      </l>
    </t>
    <t p="1" n="436" a="[3]" o="n-s---na-" u="16">
      <f>σῶμα</f>
      <l i="16074">
        <l1 o="n--s---na-">σῶμα</l1>
      </l>
    </t>
    <t p="1" n="437" a="[38]" o="u--------" u="17" join="b">
      <f>,</f>
      <l>
        <l2>,</l2>
      </l>
    </t>
    <t p="1" n="438" a="[2]" o="v3spia---" u="18">
      <f>χρὴ</f>
      <l i="8650">
        <l1 o="v-3spia---">χρή</l1>
      </l>
    </t>
    <t p="1" n="439" a="[1]" o="d--------" u="19">
      <f>δήπου</f>
      <l i="30303"/>
    </t>
    <t p="1" n="440" a="[1]" o="l-p---na-" u="20">
      <f>τὰ</f>
      <l i="1233">
        <l2>ὁ</l2>
      </l>
    </t>
    <t p="1" n="441" a="[1]" o="v-pppana-" u="21">
      <f>πυκνοῦντα</f>
      <l i="425229"/>
    </t>
    <t p="1" n="442" a="[26]" o="d--------" u="22">
      <f>καὶ</f>
      <l i="13">
        <l1 o="d---------">καί</l1>
      </l>
    </t>
    <t p="1" n="443" a="[1]" o="v-pppana-" u="23">
      <f>θερμαίνοντα</f>
      <l i="395909">
        <l1 o="v--pppana-">θερμαίνω</l1>
      </l>
    </t>
    <t p="1" n="444" a="[27]" o="d--------" u="24">
      <f>καὶ</f>
      <l i="13">
        <l1 o="d---------">καί</l1>
      </l>
    </t>
    <t p="1" n="445" a="[8]" o="l-s---fa-" u="25">
      <f>τὴν</f>
      <l>
        <l2>ὁ</l2>
      </l>
    </t>
    <t p="1" n="446" a="[3]" o="n-s---fa-" u="26">
      <f>δύναμιν</f>
      <l i="15592">
        <l1 o="n--s---fa-">δύναμις</l1>
      </l>
    </t>
    <t p="1" n="447" a="[1]" o="v-sapama-" u="27">
      <f>ἀναῤῥωννύντα</f>
      <l i="425230"/>
    </t>
    <t p="1" n="448" a="[1]" o="v--pne---" u="28">
      <f>προσφέρεσθαι</f>
      <l i="20956">
        <l1 o="v---pne---">προσφέρω</l1>
      </l>
    </t>
    <t p="1" n="449" a="[39]" o="u--------" u="29" join="b">
      <f>,</f>
      <l>
        <l2>,</l2>
      </l>
    </t>
    <t p="1" n="450" a="[28]" o="d--------" u="30">
      <f>καὶ</f>
      <l i="13">
        <l1 o="d---------">καί</l1>
      </l>
    </t>
    <t p="1" n="451" a="[1]" o="p-p---ma-" u="31">
      <f>τούτους</f>
      <l i="16152">
        <l1 o="pd-p---ma-">οὗτος</l1>
      </l>
    </t>
    <t p="1" n="452" a="[1]" o="v--pna---" u="32">
      <f>εἶναι</f>
      <l i="4014">
        <l1 o="vc--pna---">εἰμί</l1>
      </l>
    </t>
    <t p="1" n="453" a="[1]" o="n-p---ma-" u="33">
      <f>σκοποὺς</f>
      <l i="39699"/>
    </t>
    <t p="1" n="454" a="[1]" o="r--------" u="34">
      <f>ἐπ’</f>
      <l>
        <l2>ἐπί</l2>
      </l>
    </t>
    <t p="1" n="455" a="[2]" o="p-p---md-" u="35">
      <f>αὐτοῖς</f>
      <l i="4850">
        <l1 o="pp-p---md-">αὐτός</l1>
      </l>
    </t>
    <t p="1" n="456" a="[16]" o="u--------" u="36" join="b">
      <f>.</f>
      <l>
        <l2>.</l2>
      </l>
    </t>
  </s>
</text>